{
  "topics": [
    "mongo",
    "nosql",
    "база данных"
  ],
  "title": "NoSQL база данных - MongoDB",
  "category": "MongoDB",
  "quizId": 17,
  "smallText": "По сути самая используемая база данных с NodeJS и самая известная нереляционная база данных. Попробуем ее изучить!",
  "text": "Для хранения данных в NodeJS обычно используется NoSQL база данных MongoDB, которая хранит JSON-подобные документы.",
  "img": {
    "src": "/img/mongodb.png"
  },
  "tasks": [
    {
      "content": {
        "type": "digest",
        "id": 48,
        "label": "MongoDB",
        "title": "Введение в базу данных MongoDB",
        "text": "В данном дайджесте вы изучите одну из наиболее популярных NoSQL баз данных - MongoDB."
      },
      "img": {
        "icon": "fa fa-reply"
      }
    },
    {
      "content": {
        "type": "quiz",
        "id": 17,
        "label": "MongoDB",
        "title": "Тестирование по MongoDB",
        "text": "Проверьте свои знания, ответив на несколько вопросов."
      },
      "img": {
        "icon": "fa fa-check",
        "style": {
          "color": "#eb4e4e"
        }
      }
    }
  ]
}
