[
  {
    "content": {
      "digestId": 32,
      "label": "STM32",
      "title": "Окружение STM32",
      "text": "В рамках данного дайджеста вы установите среду разработки и подготовите окружение для микроконтроллера STM32."
    },
    "img": {
      "src": "/img/stm32.png"
    }
  },
  {
    "content": {
      "digestId": 33,
      "label": "STM32",
      "title": "Разработка на STM32",
      "text": "В рамках данного дайджеста вы разработаете свою первую программу, изучите прерывания и интерфейсы микроконтроллера STM32."
    },
    "img": {
      "src": "/img/stm32.png"
    }
  }
]
